zip_unicode/__init__.py
zip_unicode/main.py
ZipUnicode-1.1.1.dist-info/LICENSE
ZipUnicode-1.1.1.dist-info/METADATA
ZipUnicode-1.1.1.dist-info/WHEEL
ZipUnicode-1.1.1.dist-info/entry_points.txt
ZipUnicode-1.1.1.dist-info/top_level.txt
ZipUnicode-1.1.1.dist-info/RECORD
